LICENSE.txt
MANIFEST.in
README.rst
setup.py
linkuxit/__init__.py
linkuxit/portafolio/__init__.py
linkuxit/portafolio/admin.py
linkuxit/portafolio/cms_app.py
linkuxit/portafolio/cms_plugins.py
linkuxit/portafolio/models.py
linkuxit/portafolio/translation.py
linkuxit/portafolio/urls.py
linkuxit/portafolio/views.py
linkuxit/portafolio/locale/es/LC_MESSAGES/django.mo
linkuxit/portafolio/locale/es/LC_MESSAGES/django.po
linkuxit/portafolio/migrations/0001_initial.py
linkuxit/portafolio/migrations/0002_auto__add_field_client_logo.py
linkuxit/portafolio/migrations/0003_auto__add_testimonial.py
linkuxit/portafolio/migrations/__init__.py
linkuxit/portafolio/templates/aldryn_portafolio/plugins/portafolio/clients.html
linkuxit/portafolio/templates/aldryn_portafolio/plugins/portafolio/portafolio.html
linkuxit/portafolio/templates/aldryn_portafolio/plugins/portafolio/services.html
linkuxit/portafolio/templates/aldryn_portafolio/plugins/portafolio/team.html
linkuxit/portafolio/templates/aldryn_portafolio/plugins/portafolio/testimonials.html
linkuxit/portafolio/templates/linkuxit/portafolio/client/detail.html
linkuxit/portafolio/templates/linkuxit/portafolio/client/list.html
linkuxit/portafolio/templates/linkuxit/portafolio/member/detail.html
linkuxit/portafolio/templates/linkuxit/portafolio/project/detail.html
linkuxit/portafolio/templates/linkuxit/portafolio/project/list.html
linkuxit/portafolio/templates/linkuxit/portafolio/service/detail.html
linkuxit/portafolio/templates/linkuxit/portafolio/service/list.html
linkuxit/portafolio/templates/linkuxit/portafolio/team/detail.html
linkuxit/portafolio/templates/linkuxit/portafolio/team/list.html
linkuxit_portafolio.egg-info/PKG-INFO
linkuxit_portafolio.egg-info/SOURCES.txt
linkuxit_portafolio.egg-info/dependency_links.txt
linkuxit_portafolio.egg-info/not-zip-safe
linkuxit_portafolio.egg-info/requires.txt
linkuxit_portafolio.egg-info/top_level.txt