Metadata-Version: 1.1
Name: linkuxit-portafolio
Version: 0.14
Summary: Portafolio with Team Addon for Aldryn
Home-page: UNKNOWN
Author: Linkux IT
Author-email: linkux-it@linkux-it.com
License: LICENSE.txt
Platform: OS Independent
Classifier: Development Status :: 2 - Pre-Alpha
Classifier: Environment :: Web Environment
Classifier: Framework :: Django
Classifier: Intended Audience :: Developers
Classifier: License :: OSI Approved :: BSD License
Classifier: Operating System :: OS Independent
Classifier: Programming Language :: Python
Classifier: Topic :: Internet :: WWW/HTTP :: Dynamic Content
Classifier: Topic :: Software Development
Classifier: Topic :: Software Development :: Libraries :: Application Frameworks
